index.py
traffic_generator_mcp-2.0.0.dist-info/licenses/LICENSE
traffic_generator_mcp-2.0.0.dist-info/METADATA
traffic_generator_mcp-2.0.0.dist-info/WHEEL
traffic_generator_mcp-2.0.0.dist-info/entry_points.txt
traffic_generator_mcp-2.0.0.dist-info/top_level.txt
traffic_generator_mcp-2.0.0.dist-info/RECORD
