Metadata-Version: 2.4
Name: traffic-generator-mcp
Version: 2.0.0
Summary: Generate load testing with k6 and Amazon Relay
Author-email: Hyeonggeun Oh <kandy@plaintexting.com>
License: MIT
Project-URL: Homepage, https://github.com/Geun-Oh/k6-mcp-server
Project-URL: Repository, https://github.com/Geun-Oh/k6-mcp-server
Project-URL: Issues, https://github.com/Geun-Oh/k6-mcp-server/issues
Keywords: k6,load-testing,performance,mcp,stress-testing,msk
Classifier: Development Status :: 4 - Beta
Classifier: Intended Audience :: Developers
Classifier: License :: OSI Approved :: MIT License
Classifier: Programming Language :: Python :: 3
Classifier: Programming Language :: Python :: 3.10
Classifier: Programming Language :: Python :: 3.11
Classifier: Programming Language :: Python :: 3.12
Classifier: Topic :: Software Development :: Libraries :: Python Modules
Classifier: Topic :: System :: Systems Administration
Requires-Python: >=3.10
License-File: LICENSE
Requires-Dist: mcp>=1.0.0
Requires-Dist: boto3>=1.40.0
Dynamic: license-file
